keyword_search/__init__.py
keyword_search/cli.py
keyword_search/query.py
keyword_search-0.0.2.dist-info/METADATA
keyword_search-0.0.2.dist-info/WHEEL
keyword_search-0.0.2.dist-info/entry_points.txt
keyword_search-0.0.2.dist-info/top_level.txt
keyword_search-0.0.2.dist-info/RECORD
