Metadata-Version: 2.1
Name: keyword-search
Version: 0.0.2
Summary: A keyword search for CSV/Excel/Pandas
Author: Frederico Schmitt Kremer
Author-email: fred.s.kremer@gmail.com
Keywords: bioinformatics machine-learning data science drug discovery QSAR
Requires-Dist: pandas
Requires-Dist: openpyxl
